expmonkey/__init__.py
expmonkey-0.0.35.dist-info/METADATA
expmonkey-0.0.35.dist-info/WHEEL
expmonkey-0.0.35.dist-info/entry_points.txt
expmonkey-0.0.35.dist-info/licenses/LICENSE
expmonkey-0.0.35.dist-info/RECORD
