Metadata-Version: 2.3
Name: expmonkey
Version: 0.0.35
Summary: A git worktree-based CLI tool for efficient management and navigation of multiple isolated experiments in parallel development workflows
Project-URL: Homepage, https://github.com/liuyibo/expmonkey
Project-URL: Issues, https://github.com/liuyibo/expmonkey/issues
Author-email: liuyibo <liuyibo1994@qq.com>
Maintainer-email: liuyibo <liuyibo1994@qq.com>
License-File: LICENSE
Keywords: branch management,code branching,code experiments,command-line interface,development tools,experiment management,git branches,git enhancements,git worktree,machine learning experiments,parallel development,project organization,research workflow,scientific experiments,version control,workspace management
Classifier: Development Status :: 4 - Beta
Classifier: License :: OSI Approved :: MIT License
Classifier: Operating System :: POSIX
Classifier: Programming Language :: Python :: 3
Requires-Python: >=3.5
Requires-Dist: argcomplete
Requires-Dist: colored
Requires-Dist: pygit2; python_version >= '3.7.0'
Requires-Dist: pygit2<1.7.0; python_version < '3.7.0'
